airmailer/__init__.py
airmailer/cli.py
airmailer/logging.py
airmailer/main.py
airmailer/message.py
airmailer/backend/__init__.py
airmailer/backend/aws.py
airmailer/backend/base.py
airmailer/backend/smtp.py
airmailer/cli/__init__.py
airmailer/cli/cli.py
airmailer-0.2.2.dist-info/AUTHORS.rst
airmailer-0.2.2.dist-info/LICENSE
airmailer-0.2.2.dist-info/METADATA
airmailer-0.2.2.dist-info/WHEEL
airmailer-0.2.2.dist-info/entry_points.txt
airmailer-0.2.2.dist-info/top_level.txt
airmailer-0.2.2.dist-info/RECORD
